hyo2.abc2-2.3.10-py3.11-nspkg.pth
hyo2/abc2/__init__.py
hyo2/abc2/app/__init__.py
hyo2/abc2/app/qt_progress.py
hyo2/abc2/app/app_style/__init__.py
hyo2/abc2/app/app_style/app_style.py
hyo2/abc2/app/app_style/media/html.css
hyo2/abc2/app/app_style/media/hyo2.css
hyo2/abc2/app/app_style/media/hyo2.xml
hyo2/abc2/app/browser/__init__.py
hyo2/abc2/app/browser/browser.py
hyo2/abc2/app/browser/download_widget.py
hyo2/abc2/app/browser/web_renderer.py
hyo2/abc2/app/noaa_support/__init__.py
hyo2/abc2/app/noaa_support/__main__.py
hyo2/abc2/app/noaa_support/noaa_s57_dialog.py
hyo2/abc2/app/noaa_support/noaa_support.py
hyo2/abc2/app/noaa_support/media/Caris_Support_Files_2023v1.zip
hyo2/abc2/app/noaa_support/media/Caris_Support_Files_2024v1.zip
hyo2/abc2/app/noaa_support/media/noaa_support.ico
hyo2/abc2/app/noaa_support/media/noaa_support.png
hyo2/abc2/app/noaa_support/media/small_info.png
hyo2/abc2/app/pkg_info/__init__.py
hyo2/abc2/app/pkg_info/pkg_info_tab.py
hyo2/abc2/app/pkg_info/media/LICENSE
hyo2/abc2/app/pkg_info/media/app_icon.png
hyo2/abc2/app/pkg_info/media/ausseabed.png
hyo2/abc2/app/pkg_info/media/authors.png
hyo2/abc2/app/pkg_info/media/bug.png
hyo2/abc2/app/pkg_info/media/ccom.png
hyo2/abc2/app/pkg_info/media/home.png
hyo2/abc2/app/pkg_info/media/hyo.png
hyo2/abc2/app/pkg_info/media/license.png
hyo2/abc2/app/pkg_info/media/manual.pdf
hyo2/abc2/app/pkg_info/media/noaa.png
hyo2/abc2/app/pkg_info/media/noaa_support.png
hyo2/abc2/app/pkg_info/media/offline_manual.png
hyo2/abc2/app/pkg_info/media/online_manual.png
hyo2/abc2/app/pkg_info/media/poweredby.png
hyo2/abc2/app/pkg_info/media/unh.png
hyo2/abc2/app/pkg_info/pkg_about/__init__.py
hyo2/abc2/app/pkg_info/pkg_about/pkg_about_dialog.py
hyo2/abc2/app/pkg_info/pkg_about/tabs/__init__.py
hyo2/abc2/app/pkg_info/pkg_about/tabs/gdal_info_tab.py
hyo2/abc2/app/pkg_info/pkg_about/tabs/general_info_tab.py
hyo2/abc2/app/pkg_info/pkg_about/tabs/license_tab.py
hyo2/abc2/app/pkg_info/pkg_about/tabs/local_environment_tab.py
hyo2.abc2-2.3.10.dist-info/AUTHORS.rst
hyo2.abc2-2.3.10.dist-info/LICENSE
hyo2.abc2-2.3.10.dist-info/METADATA
hyo2.abc2-2.3.10.dist-info/WHEEL
hyo2.abc2-2.3.10.dist-info/namespace_packages.txt
hyo2.abc2-2.3.10.dist-info/top_level.txt
hyo2.abc2-2.3.10.dist-info/RECORD
