Metadata-Version: 2.1
Name: hyo2.abc2
Version: 2.3.10
Summary: Common elements for HydrOffice libraries and applications.
Home-page: https://www.hydroffice.org
Author: Giuseppe Masetti
Author-email: gmasetti@ccom.unh.edu
License: LGPLv3 license
Keywords: hydrography ocean mapping
Classifier: Development Status :: 5 - Production/Stable
Classifier: Intended Audience :: Science/Research
Classifier: Natural Language :: English
Classifier: License :: OSI Approved :: GNU Lesser General Public License v3 (LGPLv3)
Classifier: Operating System :: OS Independent
Classifier: Programming Language :: Python
Classifier: Programming Language :: Python :: 3
Classifier: Programming Language :: Python :: 3.8
Classifier: Programming Language :: Python :: 3.9
Classifier: Programming Language :: Python :: 3.10
Classifier: Programming Language :: Python :: 3.11
Classifier: Topic :: Scientific/Engineering :: GIS
Requires-Python: >=3.8
License-File: LICENSE
License-File: AUTHORS.rst
Requires-Dist: appdirs
Requires-Dist: gdal
Requires-Dist: matplotlib
Requires-Dist: numpy
Requires-Dist: psutil
Requires-Dist: pyproj
Requires-Dist: PySide6
Requires-Dist: qt-material
Requires-Dist: requests
Requires-Dist: pywin32 ; platform_system == "Windows"
